credits/__init__.py
credits-0.0.1.dist-info/LICENSE
credits-0.0.1.dist-info/METADATA
credits-0.0.1.dist-info/WHEEL
credits-0.0.1.dist-info/top_level.txt
credits-0.0.1.dist-info/RECORD
