Metadata-Version: 2.1
Name: credits
Version: 0.0.1
Summary: Verification of data together with meticulous tracing of its' sources
Home-page: https://github.com/alxfed/credits
Author: Alex Fedotov
Author-email: alex.fedotov@aol.com
License: UNKNOWN
Platform: UNKNOWN
Classifier: Programming Language :: Python :: 3
Classifier: License :: OSI Approved :: MIT License
Classifier: Operating System :: OS Independent
Requires-Python: >=3.8
